README.md
setup.py
med_face_reconstruction.egg-info/PKG-INFO
med_face_reconstruction.egg-info/SOURCES.txt
med_face_reconstruction.egg-info/dependency_links.txt
med_face_reconstruction.egg-info/top_level.txt
medface3d/__init__.py
medface3d/face_mesh_reconstruction.py
medface3d/face_pose_estimation.py
medface3d/shape_feature_extraction.py
medface3d/texture_extraction.py
simualte/__init__.py
simualte/simuator.py
utils/__init__.py
utils/get_uv_map.py
utils/interpolation.py
utils/render_mesh.py
utils/save_mesh.py
utils/transform.py
utils/visualize.py